Metadata-Version: 2.4
Name: mindframe-ai
Version: 0.2.2
Summary: Industrial-grade project scaffolding tool for Generative AI and Agentic AI developers.
Author-email: Ahmed Malik <ahmedmalik786414@gmail.com>
License: MIT
Project-URL: Homepage, https://github.com/Ahmedmalik414/mindframe
Project-URL: Repository, https://github.com/Ahmedmalik414/mindframe
Project-URL: Issues, https://github.com/Ahmedmalik414/mindframe/issues
Keywords: genai,ai,agents,scaffolding,llm,rag,orchestration
Classifier: Development Status :: 4 - Beta
Classifier: Intended Audience :: Developers
Classifier: License :: OSI Approved :: MIT License
Classifier: Programming Language :: Python :: 3
Classifier: Programming Language :: Python :: 3.8
Classifier: Programming Language :: Python :: 3.9
Classifier: Programming Language :: Python :: 3.10
Classifier: Programming Language :: Python :: 3.11
Classifier: Programming Language :: Python :: 3.12
Classifier: Topic :: Scientific/Engineering :: Artificial Intelligence
Classifier: Topic :: Software Development :: Libraries :: Python Modules
Requires-Python: >=3.8
